Metadata-Version: 2.1
Name: hotvect
Version: 2.0.0.dev0
Summary: Hotvect python interface
Home-page: https://github.com/eshioji/hotvect
Author: Enno Shioji
Author-email: eshioji@gmail.com
License: Apache License 2.0
Platform: UNKNOWN
License-File: LICENSE
